previewlink_helper/__init__.py
previewlink_helper/compose.py
previewlink_helper/exceptions.py
previewlink_helper/grabber.py
previewlink_helper/helpers.py
previewlink_helper/link.py
previewlink_helper/linkpreview.py
previewlink_helper/preview/__init__.py
previewlink_helper/preview/base.py
previewlink_helper/preview/generic.py
previewlink_helper/preview/jsonld.py
previewlink_helper/preview/metabase.py
previewlink_helper/preview/microdata.py
previewlink_helper/preview/opengraph.py
previewlink_helper/preview/schemabase.py
previewlink_helper/preview/twittercard.py
previewlink_helper-0.0.3.dist-info/METADATA
previewlink_helper-0.0.3.dist-info/WHEEL
previewlink_helper-0.0.3.dist-info/licenses/LICENSE
previewlink_helper-0.0.3.dist-info/RECORD
