Metadata-Version: 2.1
Name: previewlink_helper
Version: 0.0.3
Summary: Get link preview
Project-URL: Homepage, https://github.com/quang-megatron/linkpreview
Project-URL: Bug Tracker, https://github.com/quang-megatron/linkpreview/issues
License-File: LICENSE
Classifier: License :: OSI Approved :: MIT License
Classifier: Operating System :: OS Independent
Classifier: Programming Language :: Python :: 3
Requires-Python: >=3.10
Requires-Dist: beanie>=1.21.0
Requires-Dist: fastapi-exception>=1.2.5
Requires-Dist: pymongo>=4.5.0
